cube_provider/__init__.py
cube_provider/hooks/__init__.py
cube_provider/hooks/cube.py
cube_provider/operators/__init__.py
cube_provider/operators/cube.py
airflow_provider_cube-0.0.1.dist-info/LICENSE
airflow_provider_cube-0.0.1.dist-info/METADATA
airflow_provider_cube-0.0.1.dist-info/WHEEL
airflow_provider_cube-0.0.1.dist-info/entry_points.txt
airflow_provider_cube-0.0.1.dist-info/top_level.txt
airflow_provider_cube-0.0.1.dist-info/RECORD
