Metadata-Version: 2.1
Name: airflow-provider-cube
Version: 0.0.1
Summary: A Cube Apache Airflow provider package built by Cube.
Home-page: https://cube.dev/
Author: Artem Lytvynov
Author-email: artem.lytvynov@cube.dev
License: Apache License 2.0
Classifier: Framework :: Apache Airflow
Classifier: Framework :: Apache Airflow :: Provider
Requires-Python: ~=3.8
License-File: LICENSE
Requires-Dist: apache-airflow >=2.3
